{
  "festivalSizes": [
    {
      "id": "Petit",
      "name": "Festival Intimiste",
      "description": "Petit festival pour un public restreint.",
      "image": "img/fete.jpg",
      "cost": 1,
      "icon": "img/plus.svg",
      "isSelected": false
    },
    {
      "id": "Moyen",
      "name": "Festival Moyen",
      "description": "Festival de taille moyenne avec ambiance conviviale.",
      "image": "img/fete.jpg",
      "cost": 2,
      "icon": "img/plus.svg",
      "isSelected": true
    },
    {
      "id": "Grand",
      "name": "Grand festival",
      "description": "Festival avec une grande capacité d'accueil.",
      "image": "img/fete.jpg",
      "cost": 3,
      "icon": "img/plus.svg",
      "isSelected": false
    }
  ],
  "ecologicalActions": [
    {
      "id": "Petit",
      "name": "Minimum légal d’actions écologiques",
      "description": "Respect du minimum légal pour les actions écologiques.",
      "image": "img/fete.jpg",
      "cost": 1,
      "icon": "img/plus.svg",
      "isSelected": false
    },
    {
      "id": "Moyen",
      "name": "Peu d’actions écologiques",
      "description": "Engagement modéré pour la transition écologique.",
      "image": "img/fete.jpg",
      "cost": 2,
      "icon": "img/plus.svg",
      "isSelected": true
    },
    {
      "id": "Grand",
      "name": "Beaucoup d’actions écologiques",
      "description": "Engagement élevé pour la transition écologique.",
      "image": "img/fete.jpg",
      "cost": 3,
      "icon": "img/plus.svg",
      "isSelected": false
    }
  ],
  "culturalMediationActions": [
    {
      "id": "Petit",
      "name": "Pas d’actions de médiation",
      "description": "Aucune action de médiation culturelle prévue.",
      "image": "img/fete.jpg",
      "cost": 0,
      "icon": "img/plus.svg",
      "isSelected": false
    },
    {
      "id": "Moyen",
      "name": "Des actions uniquement sur le festival",
      "description": "Éduquer et sensibiliser les jeunes à la culture.",
      "image": "img/fete.jpg",
      "cost": 1,
      "icon": "img/plus.svg",
      "isSelected": false
    },
    {
      "id": "Grand",
      "name": "Des actions tout au long de l’année et pendant le festival",
      "description": "Créer des opportunités d'échange avec les artistes.",
      "image": "img/fete.jpg",
      "cost": 2,
      "icon": "img/plus.svg",
      "isSelected": true
    }
  ],
  "riskPreventionActions": [
    {
      "id": "Petit",
      "name": "Minimum légal d’actions de prévention",
      "description": "Respect du minimum légal pour la prévention.",
      "image": "img/fete.jpg",
      "cost": 1,
      "icon": "img/plus.svg",
      "isSelected": false
    },
    {
      "id": "Moyen",
      "name": "Réduire le nombre d’actions de prévention",
      "description": "Prévention modérée.",
      "image": "img/fete.jpg",
      "cost": 2,
      "icon": "img/plus.svg",
      "isSelected": false
    },
    {
      "id": "Grand",
      "name": "Mener activement des actions de prévention",
      "description": "Engagement fort pour la sécurité.",
      "image": "img/fete.jpg",
      "cost": 3,
      "icon": "img/plus.svg",
      "isSelected": true
    }
  ]
}